mailboxzero/__init__.py
mailboxzero-0.0.1.dist-info/LICENSE
mailboxzero-0.0.1.dist-info/METADATA
mailboxzero-0.0.1.dist-info/WHEEL
mailboxzero-0.0.1.dist-info/entry_points.txt
mailboxzero-0.0.1.dist-info/top_level.txt
mailboxzero-0.0.1.dist-info/RECORD
