Metadata-Version: 2.1
Name: mailboxzero
Version: 0.0.1
Summary: A simple smtp and webserver for throwaway email addresses
Home-page: https://github.com/betatim/mailboxzero
Author: Tim Head
Author-email: betatim@gmail.com
License: UNKNOWN
Platform: UNKNOWN
Classifier: Programming Language :: Python :: 3
Classifier: License :: OSI Approved :: BSD License
Classifier: Operating System :: OS Independent
Requires-Python: >=3.8
Requires-Dist: aiosmtpd
Requires-Dist: tornado
Requires-Dist: urlextract
